LICENSE
MANIFEST.in
README.md
setup.py
deltapd/__init__.py
deltapd/__main__.py
deltapd/cli.py
deltapd/common.py
deltapd/config.py
deltapd/exceptions.py
deltapd/logging.py
deltapd/main.py
deltapd/method.py
deltapd/model.cpp
deltapd/model.pxd
deltapd/model.pyx
deltapd/model_test.cpp
deltapd/model_test.pyx
deltapd/struct.pxd
deltapd/util.cpp
deltapd/util.pxd
deltapd/util.pyx
deltapd/util_test.cpp
deltapd/util_test.pyx
deltapd.egg-info/PKG-INFO
deltapd.egg-info/SOURCES.txt
deltapd.egg-info/dependency_links.txt
deltapd.egg-info/entry_points.txt
deltapd.egg-info/requires.txt
deltapd.egg-info/top_level.txt
deltapd/file/__init__.py
deltapd/file/metadata.py
deltapd/templates/accordion.html
deltapd/templates/index.html
deltapd/templates/template.html
deltapd/templates/assets/css/main.css
deltapd/templates/assets/css/tooltip.css
deltapd/templates/assets/js/main.js
deltapd/templates/static/font/Roboto/LICENSE.txt
deltapd/templates/static/font/Roboto/Roboto-Regular.ttf
deltapd/templates/static/img/deltapd.svg
tests/__init__.py
tests/profile.py
tests/test_model.py
tests/test_util.py