Metadata-Version: 2.1
Name: deltapd
Version: 0.1.5
Summary: deltapd
Home-page: https://github.com/Ecogenomics/deltapd
Author: Aaron Mussig
Author-email: aaronmussig@gmail.com
License: AGPL-3.0-only
Project-URL: Bug Tracker, https://github.com/Ecogenomics/deltapd/issues
Project-URL: Documentation, https://github.com/Ecogenomics/deltapd
Project-URL: Source Code, https://github.com/Ecogenomics/deltapd
Keywords: deltapd
Platform: UNKNOWN
Classifier: Development Status :: 4 - Beta
Classifier: Intended Audience :: Science/Research
Classifier: License :: OSI Approved :: GNU General Public License v3 (GPLv3)
Classifier: Natural Language :: English
Classifier: Operating System :: OS Independent
Classifier: Programming Language :: Python :: 3.6
Classifier: Topic :: Scientific/Engineering :: Bio-Informatics
Requires-Python: >=3.6
